yamlex/__init__.py
yamlex/__main__.py
yamlex/api/__init__.py
yamlex/api/differ.py
yamlex/api/exceptions.py
yamlex/api/joiner.py
yamlex/api/mapper.py
yamlex/api/splitter.py
yamlex/api/util.py
yamlex/cli/__init__.py
yamlex/cli/app.py
yamlex/cli/common_flags.py
yamlex/cli/version.py
yamlex/cli/commands/__init__.py
yamlex/cli/commands/diff.py
yamlex/cli/commands/join.py
yamlex/cli/commands/map.py
yamlex/cli/commands/split.py
yamlex-1.3.0.dist-info/METADATA
yamlex-1.3.0.dist-info/WHEEL
yamlex-1.3.0.dist-info/entry_points.txt
yamlex-1.3.0.dist-info/licenses/LICENSE
yamlex-1.3.0.dist-info/RECORD
