Metadata-Version: 2.4
Name: yamlex
Version: 1.3.0
Summary: Dynatrace Extensions: assemble extension.yaml from individual parts
Project-URL: Documentation, https://github.com/dynatrace-extensions/dt-extensions-yamlex
Project-URL: Repository, https://github.com/dynatrace-extensions/dt-extensions-yamlex
Project-URL: Issues, https://github.com/dynatrace-extensions/dt-extensions-yamlex/issues
Author-email: Vagiz Duseev <vagiz.duseev@dynatrace.com>
Maintainer-email: Vagiz Duseev <vagiz.duseev@dynatrace.com>
License-Expression: Apache-2.0
License-File: LICENSE
Keywords: cli,dynatrace,extensions
Requires-Python: >=3.9
Requires-Dist: deepdiff>=8.4
Requires-Dist: ruamel-yaml>=0.18
Requires-Dist: typer>=0.9
